{
	"data": [
		{
			"title": "Ditto",
			"rank": "1",
			"lastWeekRank": "--",
			"albumImg": "https://i.ytimg.com/vi/pSUydWEqKwE/mqdefault.jpg",
			"singer": "NewJeans",
			"chartDuration": "1주",
			"views": "2.84M",
			"link": "https://www.youtube.com/watch?v=pSUydWEqKwE"
		},
		{
			"title": "Ditto",
			"rank": "2",
			"lastWeekRank": "--",
			"albumImg": "https://i.ytimg.com/vi/V37TaRdVUQY/mqdefault.jpg",
			"singer": "NewJeans",
			"chartDuration": "1주",
			"views": "1.97M",
			"link": "https://www.youtube.com/watch?v=V37TaRdVUQY"
		},
		{
			"title": "Candy",
			"rank": "3",
			"lastWeekRank": "--",
			"albumImg": "https://i.ytimg.com/vi/zuoSn3ObMz4/mqdefault.jpg",
			"singer": "NCT DREAM",
			"chartDuration": "1주",
			"views": "1.47M",
			"link": "https://www.youtube.com/watch?v=zuoSn3ObMz4"
		},
		{
			"title": "Beautiful Christmas",
			"rank": "4",
			"lastWeekRank": "지난주 #1",
			"albumImg": "https://i.ytimg.com/vi/iTgcp1oDk2M/mqdefault.jpg",
			"singer": "Red Velvet and aespa",
			"chartDuration": "2주",
			"views": "922K",
			"link": "https://www.youtube.com/watch?v=iTgcp1oDk2M"
		},
		{
			"title": "사건의 지평선",
			"rank": "5",
			"lastWeekRank": "지난주 #3",
			"albumImg": "https://i.ytimg.com/vi/BBdC1rl5sKY/mqdefault.jpg",
			"singer": "윤하",
			"chartDuration": "32주",
			"views": "646K",
			"link": "https://www.youtube.com/watch?v=BBdC1rl5sKY"
		},
		{
			"title": "London Boy",
			"rank": "6",
			"lastWeekRank": "지난주 #4",
			"albumImg": "https://i.ytimg.com/vi/TMfvkhkALbU/mqdefault.jpg",
			"singer": "임영웅",
			"chartDuration": "6주",
			"views": "583K",
			"link": "https://www.youtube.com/watch?v=TMfvkhkALbU"
		},
		{
			"title": "정국 (Jung Kook) Dreamers @ FIFA World Cup Qatar 2022 Opening Ceremony",
			"rank": "7",
			"lastWeekRank": "지난주 #2",
			"albumImg": "https://i.ytimg.com/vi/jEdfjuG0Fx4/mqdefault.jpg",
			"singer": "BTS(방탄소년단) and Jung Kook",
			"chartDuration": "5주",
			"views": "525K",
			"link": "https://www.youtube.com/watch?v=jEdfjuG0Fx4"
		},
		{
			"title": "After LIKE",
			"rank": "8",
			"lastWeekRank": "지난주 #7",
			"albumImg": "https://i.ytimg.com/vi/F0B7HDiY-10/mqdefault.jpg",
			"singer": "IVE (아이브)",
			"chartDuration": "18주",
			"views": "495K",
			"link": "https://www.youtube.com/watch?v=F0B7HDiY-10"
		},
		{
			"title": "Polaroid",
			"rank": "9",
			"lastWeekRank": "지난주 #5",
			"albumImg": "https://i.ytimg.com/vi/I82pbW2y_cc/mqdefault.jpg",
			"singer": "임영웅",
			"chartDuration": "6주",
			"views": "487K",
			"link": "https://www.youtube.com/watch?v=I82pbW2y_cc"
		},
		{
			"title": "Nxde",
			"rank": "10",
			"lastWeekRank": "지난주 #6",
			"albumImg": "https://i.ytimg.com/vi/fCO7f0SmrDc/mqdefault.jpg",
			"singer": "(여자)아이들",
			"chartDuration": "10주",
			"views": "483K",
			"link": "https://www.youtube.com/watch?v=fCO7f0SmrDc"
		},
		{
			"title": "Polaroid",
			"rank": "11",
			"lastWeekRank": "--",
			"albumImg": "https://i.ytimg.com/vi/NaofZasYCjo/mqdefault.jpg",
			"singer": "임영웅",
			"chartDuration": "1주",
			"views": "460K",
			"link": "https://www.youtube.com/watch?v=NaofZasYCjo"
		},
		{
			"title": "푸른꽃",
			"rank": "12",
			"lastWeekRank": "--",
			"albumImg": "https://i.ytimg.com/vi/fvTHBV0XIIk/mqdefault.jpg",
			"singer": "리아 (ITZY)",
			"chartDuration": "1주",
			"views": "384K",
			"link": "https://www.youtube.com/watch?v=fvTHBV0XIIk"
		},
		{
			"title": "다시 만날 수 있을까",
			"rank": "13",
			"lastWeekRank": "지난주 #10",
			"albumImg": "https://i.ytimg.com/vi/sHqFqWDviBg/mqdefault.jpg",
			"singer": "임영웅",
			"chartDuration": "34주",
			"views": "374K",
			"link": "https://www.youtube.com/watch?v=sHqFqWDviBg"
		},
		{
			"title": "Dreamers (FIFA World Cup 2022 Soundtrack)",
			"rank": "14",
			"lastWeekRank": "지난주 #8",
			"albumImg": "https://i.ytimg.com/vi/IwzkfMmNMpM/mqdefault.jpg",
			"singer": "Jung Kook and BTS",
			"chartDuration": "4주",
			"views": "352K",
			"link": "https://www.youtube.com/watch?v=IwzkfMmNMpM"
		},
		{
			"title": "ANTIFRAGILE",
			"rank": "15",
			"lastWeekRank": "지난주 #13",
			"albumImg": "https://i.ytimg.com/vi/pyf8cbqyfPs/mqdefault.jpg",
			"singer": "르세라핌",
			"chartDuration": "10주",
			"views": "316K",
			"link": "https://www.youtube.com/watch?v=pyf8cbqyfPs"
		},
		{
			"title": "London Boy",
			"rank": "16",
			"lastWeekRank": "지난주 #9",
			"albumImg": "https://i.ytimg.com/vi/hTPpQX9FEDE/mqdefault.jpg",
			"singer": "임영웅",
			"chartDuration": "2주",
			"views": "315K",
			"link": "https://www.youtube.com/watch?v=hTPpQX9FEDE"
		},
		{
			"title": "우리들의블루스",
			"rank": "17",
			"lastWeekRank": "지난주 #12",
			"albumImg": "https://i.ytimg.com/vi/JPPIrXdocjQ/mqdefault.jpg",
			"singer": "임영웅",
			"chartDuration": "36주",
			"views": "314K",
			"link": "https://www.youtube.com/watch?v=JPPIrXdocjQ"
		},
		{
			"title": "아버지",
			"rank": "18",
			"lastWeekRank": "지난주 #11",
			"albumImg": "https://i.ytimg.com/vi/An7ZnTEz40s/mqdefault.jpg",
			"singer": "임영웅",
			"chartDuration": "20주",
			"views": "294K",
			"link": "https://www.youtube.com/watch?v=An7ZnTEz40s"
		},
		{
			"title": "곶감이다 (Duet with 지광민)",
			"rank": "19",
			"lastWeekRank": "--",
			"albumImg": "https://i.ytimg.com/vi/6ByjXKSdGTM/mqdefault.jpg",
			"singer": "영탁",
			"chartDuration": "1주",
			"views": "287K",
			"link": "https://www.youtube.com/watch?v=6ByjXKSdGTM"
		},
		{
			"title": "When I Get Old",
			"rank": "20",
			"lastWeekRank": "지난주 #14",
			"albumImg": "https://i.ytimg.com/vi/Ua3aNDJE_Cg/mqdefault.jpg",
			"singer": "크리스토퍼 and 청하",
			"chartDuration": "9주",
			"views": "247K",
			"link": "https://www.youtube.com/watch?v=Ua3aNDJE_Cg"
		},
		{
			"title": "Hype Boy (Performance ver.1)",
			"rank": "21",
			"lastWeekRank": "지난주 #31",
			"albumImg": "https://i.ytimg.com/vi/11cta61wi0g/mqdefault.jpg",
			"singer": "NewJeans",
			"chartDuration": "19주",
			"views": "241K",
			"link": "https://www.youtube.com/watch?v=11cta61wi0g"
		},
		{
			"title": "Kawaikutegomen",
			"rank": "22",
			"lastWeekRank": "지난주 #16",
			"albumImg": "https://i.ytimg.com/vi/K4xLi8IF1FM/mqdefault.jpg",
			"singer": "HoneyWorks",
			"chartDuration": "5주",
			"views": "238K",
			"link": "https://www.youtube.com/watch?v=K4xLi8IF1FM"
		},
		{
			"title": "My Name Is Money",
			"rank": "23",
			"lastWeekRank": "--",
			"albumImg": "https://i.ytimg.com/vi/j3G0js1VKsI/mqdefault.jpg",
			"singer": "애쉬비",
			"chartDuration": "1주",
			"views": "235K",
			"link": "https://www.youtube.com/watch?v=j3G0js1VKsI"
		},
		{
			"title": "[김호중X에스페로] Endless 풀버전 무대 영상 공개",
			"rank": "24",
			"lastWeekRank": "--",
			"albumImg": "https://i.ytimg.com/vi/sJFB7JBatHE/mqdefault.jpg",
			"singer": "김호중",
			"chartDuration": "1주",
			"views": "210K",
			"link": "https://www.youtube.com/watch?v=sJFB7JBatHE"
		},
		{
			"title": "날개 (Prod. 영탁) (Inst.)",
			"rank": "25",
			"lastWeekRank": "지난주 #34",
			"albumImg": "https://i.ytimg.com/vi/PjGvvGBIsZM/mqdefault.jpg",
			"singer": "오혜빈, 영탁, 강대웅, 하동근, 광석 and 송근안",
			"chartDuration": "2주",
			"views": "203K",
			"link": "https://www.youtube.com/watch?v=PjGvvGBIsZM"
		},
		{
			"title": "담 (The Wall) \"Live\"",
			"rank": "26",
			"lastWeekRank": "지난주 #35",
			"albumImg": "https://i.ytimg.com/vi/lHTiJt-Z2hk/mqdefault.jpg",
			"singer": "영탁",
			"chartDuration": "20주",
			"views": "177K",
			"link": "https://www.youtube.com/watch?v=lHTiJt-Z2hk"
		},
		{
			"title": "사랑해 진짜",
			"rank": "27",
			"lastWeekRank": "지난주 #22",
			"albumImg": "https://i.ytimg.com/vi/CbhiBN5wpCc/mqdefault.jpg",
			"singer": "임영웅",
			"chartDuration": "9주",
			"views": "174K",
			"link": "https://www.youtube.com/watch?v=CbhiBN5wpCc"
		},
		{
			"title": "무지개",
			"rank": "28",
			"lastWeekRank": "지난주 #23",
			"albumImg": "https://i.ytimg.com/vi/jP2J0qnFtV4/mqdefault.jpg",
			"singer": "임영웅",
			"chartDuration": "30주",
			"views": "173K",
			"link": "https://www.youtube.com/watch?v=jP2J0qnFtV4"
		},
		{
			"title": "연애편지",
			"rank": "29",
			"lastWeekRank": "지난주 #24",
			"albumImg": "https://i.ytimg.com/vi/P2FcQvCbDWg/mqdefault.jpg",
			"singer": "임영웅",
			"chartDuration": "31주",
			"views": "173K",
			"link": "https://www.youtube.com/watch?v=P2FcQvCbDWg"
		},
		{
			"title": "LOVE DIVE",
			"rank": "30",
			"lastWeekRank": "지난주 #19",
			"albumImg": "https://i.ytimg.com/vi/Y8JFxS1HlDo/mqdefault.jpg",
			"singer": "IVE (아이브)",
			"chartDuration": "37주",
			"views": "170K",
			"link": "https://www.youtube.com/watch?v=Y8JFxS1HlDo"
		},
		{
			"title": "Shut Down",
			"rank": "31",
			"lastWeekRank": "지난주 #26",
			"albumImg": "https://i.ytimg.com/vi/POe9SOEKotk/mqdefault.jpg",
			"singer": "BLACKPINK",
			"chartDuration": "14주",
			"views": "168K",
			"link": "https://www.youtube.com/watch?v=POe9SOEKotk"
		},
		{
			"title": "편의점",
			"rank": "32",
			"lastWeekRank": "지난주 #32",
			"albumImg": "https://i.ytimg.com/vi/G_m__AKDFKw/mqdefault.jpg",
			"singer": "이찬원",
			"chartDuration": "38주",
			"views": "163K",
			"link": "https://www.youtube.com/watch?v=G_m__AKDFKw"
		},
		{
			"title": "Cheshire",
			"rank": "33",
			"lastWeekRank": "지난주 #20",
			"albumImg": "https://i.ytimg.com/vi/zugAhfd2r0g/mqdefault.jpg",
			"singer": "ITZY",
			"chartDuration": "4주",
			"views": "163K",
			"link": "https://www.youtube.com/watch?v=zugAhfd2r0g"
		},
		{
			"title": "Face",
			"rank": "34",
			"lastWeekRank": "지난주 #37",
			"albumImg": "https://i.ytimg.com/vi/gyXy0m-4bvE/mqdefault.jpg",
			"singer": "뉴이스트(NUEST)",
			"chartDuration": "5주",
			"views": "163K",
			"link": "https://www.youtube.com/watch?v=gyXy0m-4bvE"
		},
		{
			"title": "Pink Venom",
			"rank": "35",
			"lastWeekRank": "지난주 #28",
			"albumImg": "https://i.ytimg.com/vi/gQlMMD8auMs/mqdefault.jpg",
			"singer": "BLACKPINK",
			"chartDuration": "18주",
			"views": "162K",
			"link": "https://www.youtube.com/watch?v=gQlMMD8auMs"
		},
		{
			"title": "이러면 안 될 거 아는데 너 앞에만 서면 나락",
			"rank": "36",
			"lastWeekRank": "지난주 #29",
			"albumImg": "https://i.ytimg.com/vi/KgOfyyaOkEs/mqdefault.jpg",
			"singer": "DINDIN",
			"chartDuration": "43주",
			"views": "160K",
			"link": "https://www.youtube.com/watch?v=KgOfyyaOkEs"
		},
		{
			"title": "TOMBOY",
			"rank": "37",
			"lastWeekRank": "지난주 #30",
			"albumImg": "https://i.ytimg.com/vi/Jh4QFaPmdss/mqdefault.jpg",
			"singer": "(여자)아이들",
			"chartDuration": "41주",
			"views": "158K",
			"link": "https://www.youtube.com/watch?v=Jh4QFaPmdss"
		},
		{
			"title": "친구",
			"rank": "38",
			"lastWeekRank": "지난주 #21",
			"albumImg": "https://i.ytimg.com/vi/tv4PNacJXsA/mqdefault.jpg",
			"singer": "김호중",
			"chartDuration": "20주",
			"views": "158K",
			"link": "https://www.youtube.com/watch?v=tv4PNacJXsA"
		},
		{
			"title": "들꽃놀이",
			"rank": "39",
			"lastWeekRank": "지난주 #15",
			"albumImg": "https://i.ytimg.com/vi/u18be_kRmC0/mqdefault.jpg",
			"singer": "RM and 조유진",
			"chartDuration": "3주",
			"views": "156K",
			"link": "https://www.youtube.com/watch?v=u18be_kRmC0"
		},
		{
			"title": "Attention",
			"rank": "40",
			"lastWeekRank": "지난주 #43",
			"albumImg": "https://i.ytimg.com/vi/js1CtxSY38I/mqdefault.jpg",
			"singer": "NewJeans",
			"chartDuration": "22주",
			"views": "156K",
			"link": "https://www.youtube.com/watch?v=js1CtxSY38I"
		},
		{
			"title": "KIM HO JOONG(김호중) 약속 MV",
			"rank": "41",
			"lastWeekRank": "지난주 #25",
			"albumImg": "https://i.ytimg.com/vi/_FVHWNdlIXY/mqdefault.jpg",
			"singer": "김호중",
			"chartDuration": "22주",
			"views": "152K",
			"link": "https://www.youtube.com/watch?v=_FVHWNdlIXY"
		},
		{
			"title": "주마등",
			"rank": "42",
			"lastWeekRank": "지난주 #27",
			"albumImg": "https://i.ytimg.com/vi/NLa9-kYadqg/mqdefault.jpg",
			"singer": "김호중",
			"chartDuration": "21주",
			"views": "151K",
			"link": "https://www.youtube.com/watch?v=NLa9-kYadqg"
		},
		{
			"title": "레볼루션 하트 흰 눈이 내려와 M/V",
			"rank": "43",
			"lastWeekRank": "--",
			"albumImg": "https://i.ytimg.com/vi/ssYoWeRyJ3I/mqdefault.jpg",
			"singer": "CHARONuniverse [카론 유니버스]",
			"chartDuration": "1주",
			"views": "150K",
			"link": "https://www.youtube.com/watch?v=ssYoWeRyJ3I"
		},
		{
			"title": "뱃놀이",
			"rank": "44",
			"lastWeekRank": "지난주 #18",
			"albumImg": "https://i.ytimg.com/vi/HpgGJyEE_20/mqdefault.jpg",
			"singer": "정동원",
			"chartDuration": "3주",
			"views": "150K",
			"link": "https://www.youtube.com/watch?v=HpgGJyEE_20"
		},
		{
			"title": "빛이 나는 사람",
			"rank": "45",
			"lastWeekRank": "지난주 #33",
			"albumImg": "https://i.ytimg.com/vi/9KpD_5wXyTs/mqdefault.jpg",
			"singer": "김호중",
			"chartDuration": "27주",
			"views": "136K",
			"link": "https://www.youtube.com/watch?v=9KpD_5wXyTs"
		},
		{
			"title": "All I Want for Christmas Is You (Make My Wish Come True Edition)",
			"rank": "46",
			"lastWeekRank": "지난주 #48",
			"albumImg": "https://i.ytimg.com/vi/aAkMkVFwAoo/mqdefault.jpg",
			"singer": "Mariah Carey",
			"chartDuration": "17주",
			"views": "136K",
			"link": "https://www.youtube.com/watch?v=aAkMkVFwAoo"
		},
		{
			"title": "That That",
			"rank": "47",
			"lastWeekRank": "지난주 #39",
			"albumImg": "https://i.ytimg.com/vi/8dJyRm2jJ-U/mqdefault.jpg",
			"singer": "싸이(Psy)",
			"chartDuration": "34주",
			"views": "131K",
			"link": "https://www.youtube.com/watch?v=8dJyRm2jJ-U"
		},
		{
			"title": "WHEN I MOVE",
			"rank": "48",
			"lastWeekRank": "지난주 #17",
			"albumImg": "https://i.ytimg.com/vi/XwcK-twSXB4/mqdefault.jpg",
			"singer": "카라(KARA)",
			"chartDuration": "4주",
			"views": "130K",
			"link": "https://www.youtube.com/watch?v=XwcK-twSXB4"
		},
		{
			"title": "[정서주] 삼천포 아가씨 + 황포돛대 + 낭주골처녀 Live Clip 『2022 정서주 1st Concert ‘꽃들에게』",
			"rank": "49",
			"lastWeekRank": "지난주 #87",
			"albumImg": "https://i.ytimg.com/vi/faLnFBc-f8Q/mqdefault.jpg",
			"singer": "트로트샛별 정서주",
			"chartDuration": "2주",
			"views": "123K",
			"link": "https://www.youtube.com/watch?v=faLnFBc-f8Q"
		},
		{
			"title": "그중에 그대를 만나",
			"rank": "50",
			"lastWeekRank": "지난주 #38",
			"albumImg": "https://i.ytimg.com/vi/_7Gd_ur2ss8/mqdefault.jpg",
			"singer": "김호중",
			"chartDuration": "11주",
			"views": "122K",
			"link": "https://www.youtube.com/watch?v=_7Gd_ur2ss8"
		},
		{
			"title": "KICKBACK",
			"rank": "51",
			"lastWeekRank": "지난주 #40",
			"albumImg": "https://i.ytimg.com/vi/M2cckDmNLMI/mqdefault.jpg",
			"singer": "Kenshi Yonezu(켄시 요네즈/米津 玄師)",
			"chartDuration": "9주",
			"views": "122K",
			"link": "https://www.youtube.com/watch?v=M2cckDmNLMI"
		},
		{
			"title": "자격지심",
			"rank": "52",
			"lastWeekRank": "지난주 #49",
			"albumImg": "https://i.ytimg.com/vi/viy213MhJeI/mqdefault.jpg",
			"singer": "BEO (비오)",
			"chartDuration": "12주",
			"views": "121K",
			"link": "https://www.youtube.com/watch?v=viy213MhJeI"
		},
		{
			"title": "안녕 김녕 (Bye Gimnyeong)",
			"rank": "53",
			"lastWeekRank": "지난주 #50",
			"albumImg": "https://i.ytimg.com/vi/laeelJADJHk/mqdefault.jpg",
			"singer": "영탁",
			"chartDuration": "22주",
			"views": "121K",
			"link": "https://www.youtube.com/watch?v=laeelJADJHk"
		},
		{
			"title": "Snowman",
			"rank": "54",
			"lastWeekRank": "지난주 #67",
			"albumImg": "https://i.ytimg.com/vi/gset79KMmt0/mqdefault.jpg",
			"singer": "Sia(시아)",
			"chartDuration": "11주",
			"views": "119K",
			"link": "https://www.youtube.com/watch?v=gset79KMmt0"
		},
		{
			"title": "Wings",
			"rank": "55",
			"lastWeekRank": "지난주 #54",
			"albumImg": "https://i.ytimg.com/vi/Tw0YmRVZOnU/mqdefault.jpg",
			"singer": "Kwang Suk, Oh Hye Bin, Kang Dae Woong, Song Geun An, Ha Dong Geun and YOUNGTAK",
			"chartDuration": "5주",
			"views": "118K",
			"link": "https://www.youtube.com/watch?v=Tw0YmRVZOnU"
		},
		{
			"title": "Unholy (Official Music Video)",
			"rank": "56",
			"lastWeekRank": "지난주 #96",
			"albumImg": "https://i.ytimg.com/vi/Uq9gPaIzbe8/mqdefault.jpg",
			"singer": "Sam Smith(샘 스미스) and Kim Petras",
			"chartDuration": "6주",
			"views": "110K",
			"link": "https://www.youtube.com/watch?v=Uq9gPaIzbe8"
		},
		{
			"title": "A bientot",
			"rank": "57",
			"lastWeekRank": "지난주 #51",
			"albumImg": "https://i.ytimg.com/vi/zLFypmn42NE/mqdefault.jpg",
			"singer": "임영웅",
			"chartDuration": "10주",
			"views": "109K",
			"link": "https://www.youtube.com/watch?v=zLFypmn42NE"
		},
		{
			"title": "Cookie",
			"rank": "58",
			"lastWeekRank": "지난주 #65",
			"albumImg": "https://i.ytimg.com/vi/VOmIplFAGeg/mqdefault.jpg",
			"singer": "NewJeans",
			"chartDuration": "21주",
			"views": "107K",
			"link": "https://www.youtube.com/watch?v=VOmIplFAGeg"
		},
		{
			"title": "오너라 이리",
			"rank": "59",
			"lastWeekRank": "지난주 #81",
			"albumImg": "https://i.ytimg.com/vi/wt0wscAxCiw/mqdefault.jpg",
			"singer": "요요미",
			"chartDuration": "5주",
			"views": "106K",
			"link": "https://www.youtube.com/watch?v=wt0wscAxCiw"
		},
		{
			"title": "Shinunoga E-Wa",
			"rank": "60",
			"lastWeekRank": "지난주 #60",
			"albumImg": "https://i.ytimg.com/vi/lRVJuPI5IXI/mqdefault.jpg",
			"singer": "후지이 카제",
			"chartDuration": "3주",
			"views": "105K",
			"link": "https://www.youtube.com/watch?v=lRVJuPI5IXI"
		},
		{
			"title": "Candy",
			"rank": "61",
			"lastWeekRank": "지난주 #69",
			"albumImg": "https://i.ytimg.com/vi/3NUaXU1d-NY/mqdefault.jpg",
			"singer": "H.O.T.",
			"chartDuration": "3주",
			"views": "103K",
			"link": "https://www.youtube.com/watch?v=3NUaXU1d-NY"
		},
		{
			"title": "Waka Waka (This Time for Africa) [The Official 2010 FIFA World World Cup Song]",
			"rank": "62",
			"lastWeekRank": "지난주 #46",
			"albumImg": "https://i.ytimg.com/vi/pRpeEdMmmQ0/mqdefault.jpg",
			"singer": "Shakira",
			"chartDuration": "5주",
			"views": "103K",
			"link": "https://www.youtube.com/watch?v=pRpeEdMmmQ0"
		},
		{
			"title": "Last Christmas",
			"rank": "63",
			"lastWeekRank": "지난주 #64",
			"albumImg": "https://i.ytimg.com/vi/E8gmARGvPlI/mqdefault.jpg",
			"singer": "Wham!",
			"chartDuration": "27주",
			"views": "101K",
			"link": "https://www.youtube.com/watch?v=E8gmARGvPlI"
		},
		{
			"title": "Made You Look",
			"rank": "64",
			"lastWeekRank": "지난주 #52",
			"albumImg": "https://i.ytimg.com/vi/gPCCYMeXin0/mqdefault.jpg",
			"singer": "Meghan Trainor",
			"chartDuration": "5주",
			"views": "101K",
			"link": "https://www.youtube.com/watch?v=gPCCYMeXin0"
		},
		{
			"title": "BIBI Vengeance",
			"rank": "65",
			"lastWeekRank": "지난주 #42",
			"albumImg": "https://i.ytimg.com/vi/58NBFWwulrk/mqdefault.jpg",
			"singer": "비비(BIBI)",
			"chartDuration": "5주",
			"views": "99.2K",
			"link": "https://www.youtube.com/watch?v=58NBFWwulrk"
		},
		{
			"title": "Kira Killer",
			"rank": "66",
			"lastWeekRank": "--",
			"albumImg": "https://i.ytimg.com/vi/e5LaKxJVeVI/mqdefault.jpg",
			"singer": "Zutomayo",
			"chartDuration": "1주",
			"views": "98.7K",
			"link": "https://www.youtube.com/watch?v=e5LaKxJVeVI"
		},
		{
			"title": "뱃놀이",
			"rank": "67",
			"lastWeekRank": "지난주 #36",
			"albumImg": "https://i.ytimg.com/vi/MReLmgu_qzk/mqdefault.jpg",
			"singer": "정동원",
			"chartDuration": "3주",
			"views": "94.3K",
			"link": "https://www.youtube.com/watch?v=MReLmgu_qzk"
		},
		{
			"title": "사건의 지평선",
			"rank": "68",
			"lastWeekRank": "--",
			"albumImg": "https://i.ytimg.com/vi/z1KLjaXHQVY/mqdefault.jpg",
			"singer": "윤하",
			"chartDuration": "1주",
			"views": "89K",
			"link": "https://www.youtube.com/watch?v=z1KLjaXHQVY"
		},
		{
			"title": "Cheshire",
			"rank": "69",
			"lastWeekRank": "--",
			"albumImg": "https://i.ytimg.com/vi/H2nb2yf0_14/mqdefault.jpg",
			"singer": "ITZY",
			"chartDuration": "1주",
			"views": "85.4K",
			"link": "https://www.youtube.com/watch?v=H2nb2yf0_14"
		},
		{
			"title": "사건의 지평선",
			"rank": "70",
			"lastWeekRank": "지난주 #92",
			"albumImg": "https://i.ytimg.com/vi/73V3xrfiYMo/mqdefault.jpg",
			"singer": "윤하",
			"chartDuration": "10주",
			"views": "82.1K",
			"link": "https://www.youtube.com/watch?v=73V3xrfiYMo"
		},
		{
			"title": "Rush Hour",
			"rank": "71",
			"lastWeekRank": "지난주 #58",
			"albumImg": "https://i.ytimg.com/vi/PS0qkO5qty0/mqdefault.jpg",
			"singer": "크러쉬",
			"chartDuration": "14주",
			"views": "80.6K",
			"link": "https://www.youtube.com/watch?v=PS0qkO5qty0"
		},
		{
			"title": "The Astronaut",
			"rank": "72",
			"lastWeekRank": "지난주 #61",
			"albumImg": "https://i.ytimg.com/vi/c6ASQOwKkhk/mqdefault.jpg",
			"singer": "Jin",
			"chartDuration": "8주",
			"views": "76.5K",
			"link": "https://www.youtube.com/watch?v=c6ASQOwKkhk"
		},
		{
			"title": "After LIKE",
			"rank": "73",
			"lastWeekRank": "지난주 #55",
			"albumImg": "https://i.ytimg.com/vi/RJpDWf4DWu8/mqdefault.jpg",
			"singer": "IVE (아이브)",
			"chartDuration": "9주",
			"views": "75.5K",
			"link": "https://www.youtube.com/watch?v=RJpDWf4DWu8"
		},
		{
			"title": "Birthday",
			"rank": "74",
			"lastWeekRank": "지난주 #44",
			"albumImg": "https://i.ytimg.com/vi/Ut1OzEVUiM4/mqdefault.jpg",
			"singer": "Red Velvet",
			"chartDuration": "4주",
			"views": "74.7K",
			"link": "https://www.youtube.com/watch?v=Ut1OzEVUiM4"
		},
		{
			"title": "못해",
			"rank": "75",
			"lastWeekRank": "지난주 #78",
			"albumImg": "https://i.ytimg.com/vi/cDisBJk9xMQ/mqdefault.jpg",
			"singer": "김나영",
			"chartDuration": "11주",
			"views": "73.7K",
			"link": "https://www.youtube.com/watch?v=cDisBJk9xMQ"
		},
		{
			"title": "New Genesis",
			"rank": "76",
			"lastWeekRank": "지난주 #53",
			"albumImg": "https://i.ytimg.com/vi/IPaSD4sQOkg/mqdefault.jpg",
			"singer": "Ado",
			"chartDuration": "3주",
			"views": "73.6K",
			"link": "https://www.youtube.com/watch?v=IPaSD4sQOkg"
		},
		{
			"title": "나쁜X",
			"rank": "77",
			"lastWeekRank": "지난주 #57",
			"albumImg": "https://i.ytimg.com/vi/QfIY1r0_tRI/mqdefault.jpg",
			"singer": "비비(BIBI)",
			"chartDuration": "5주",
			"views": "73K",
			"link": "https://www.youtube.com/watch?v=QfIY1r0_tRI"
		},
		{
			"title": "STEP",
			"rank": "78",
			"lastWeekRank": "지난주 #63",
			"albumImg": "https://i.ytimg.com/vi/zYoYoBtLqOY/mqdefault.jpg",
			"singer": "카라(KARA)",
			"chartDuration": "5주",
			"views": "72.4K",
			"link": "https://www.youtube.com/watch?v=zYoYoBtLqOY"
		},
		{
			"title": "요요미 - 그순간 (김범룡) Cover by YOYOMI",
			"rank": "79",
			"lastWeekRank": "--",
			"albumImg": "https://i.ytimg.com/vi/xFdwG3j0xnQ/mqdefault.jpg",
			"singer": "요요미",
			"chartDuration": "4주",
			"views": "72.4K",
			"link": "https://www.youtube.com/watch?v=xFdwG3j0xnQ"
		},
		{
			"title": "X JAPAN 『ENDLESS RAIN』（HD）",
			"rank": "80",
			"lastWeekRank": "지난주 #71",
			"albumImg": "https://i.ytimg.com/vi/QhOFg_3RV5Q/mqdefault.jpg",
			"singer": "X Japan(엑스 재팬)",
			"chartDuration": "4주",
			"views": "71.5K",
			"link": "https://www.youtube.com/watch?v=QhOFg_3RV5Q"
		},
		{
			"title": "Talk that Talk",
			"rank": "81",
			"lastWeekRank": "지난주 #72",
			"albumImg": "https://i.ytimg.com/vi/k6jqx9kZgPM/mqdefault.jpg",
			"singer": "TWICE(트와이스)",
			"chartDuration": "17주",
			"views": "69.8K",
			"link": "https://www.youtube.com/watch?v=k6jqx9kZgPM"
		},
		{
			"title": "BTS (방탄소년단) 달려라 방탄 (Run BTS) @ BTS \"Yet To Come\" in BUSAN",
			"rank": "82",
			"lastWeekRank": "지난주 #56",
			"albumImg": "https://i.ytimg.com/vi/Cb70gcTVvYI/mqdefault.jpg",
			"singer": "BTS(방탄소년단)",
			"chartDuration": "10주",
			"views": "69.1K",
			"link": "https://www.youtube.com/watch?v=Cb70gcTVvYI"
		},
		{
			"title": "DICE",
			"rank": "83",
			"lastWeekRank": "지난주 #74",
			"albumImg": "https://i.ytimg.com/vi/p1bjnyDqI9k/mqdefault.jpg",
			"singer": "엔믹스",
			"chartDuration": "14주",
			"views": "67.9K",
			"link": "https://www.youtube.com/watch?v=p1bjnyDqI9k"
		},
		{
			"title": "불륜",
			"rank": "84",
			"lastWeekRank": "지난주 #59",
			"albumImg": "https://i.ytimg.com/vi/wqGr9_zh0S0/mqdefault.jpg",
			"singer": "비비(BIBI)",
			"chartDuration": "9주",
			"views": "66.8K",
			"link": "https://www.youtube.com/watch?v=wqGr9_zh0S0"
		},
		{
			"title": "떠나보낼 준비해 둘걸 그랬어",
			"rank": "85",
			"lastWeekRank": "지난주 #82",
			"albumImg": "https://i.ytimg.com/vi/5rO-t7u6OE4/mqdefault.jpg",
			"singer": "임한별",
			"chartDuration": "8주",
			"views": "65.3K",
			"link": "https://www.youtube.com/watch?v=5rO-t7u6OE4"
		},
		{
			"title": "사랑 너였니 (Love, was it you?)",
			"rank": "86",
			"lastWeekRank": "지난주 #73",
			"albumImg": "https://i.ytimg.com/vi/5omYN5Ay_Qc/mqdefault.jpg",
			"singer": "장민호 ",
			"chartDuration": "7주",
			"views": "64.3K",
			"link": "https://www.youtube.com/watch?v=5omYN5Ay_Qc"
		},
		{
			"title": "CHRISTMAS WORSHIP | 기쁘다 구주 오셨네 and 참 반가운 신도여 | SOLA SCRIPTURA | OPEN WORSHIP",
			"rank": "87",
			"lastWeekRank": "--",
			"albumImg": "https://i.ytimg.com/vi/zcZEny-rKOk/mqdefault.jpg",
			"singer": "아이자야씩스티원 (Isaiah 6tyOne)",
			"chartDuration": "1주",
			"views": "63.5K",
			"link": "https://www.youtube.com/watch?v=zcZEny-rKOk"
		},
		{
			"title": "숨겨진 세상 (From “겨울왕국 2”/Sing-Along)",
			"rank": "88",
			"lastWeekRank": "지난주 #85",
			"albumImg": "https://i.ytimg.com/vi/xTzaswTXXe0/mqdefault.jpg",
			"singer": "박혜나 and AURORA",
			"chartDuration": "15주",
			"views": "63.1K",
			"link": "https://www.youtube.com/watch?v=xTzaswTXXe0"
		},
		{
			"title": "Nothing Is Lost (You Give Me Strength)",
			"rank": "89",
			"lastWeekRank": "--",
			"albumImg": "https://i.ytimg.com/vi/bDHD1ueL4a4/mqdefault.jpg",
			"singer": "The Weeknd",
			"chartDuration": "1주",
			"views": "61.9K",
			"link": "https://www.youtube.com/watch?v=bDHD1ueL4a4"
		},
		{
			"title": "BTS (방탄소년단) Butter @ The 64th GRAMMY Awards",
			"rank": "90",
			"lastWeekRank": "지난주 #79",
			"albumImg": "https://i.ytimg.com/vi/HbkBVxU5K5A/mqdefault.jpg",
			"singer": "BTS(방탄소년단)",
			"chartDuration": "14주",
			"views": "61.4K",
			"link": "https://www.youtube.com/watch?v=HbkBVxU5K5A"
		},
		{
			"title": "Into the Unknown (From \"Frozen 2\")",
			"rank": "91",
			"lastWeekRank": "--",
			"albumImg": "https://i.ytimg.com/vi/gIOyB9ZXn8s/mqdefault.jpg",
			"singer": "Idina Menzel and AURORA",
			"chartDuration": "23주",
			"views": "60.4K",
			"link": "https://www.youtube.com/watch?v=gIOyB9ZXn8s"
		},
		{
			"title": "빛 (Hope from KWANGYA) Self-Camera Video | SMTOWN LIVE 2022 : SMCU EXPRESS @ TOKYO",
			"rank": "92",
			"lastWeekRank": "--",
			"albumImg": "https://i.ytimg.com/vi/VWzRVC3v20Y/mqdefault.jpg",
			"singer": "SMTOWN",
			"chartDuration": "1주",
			"views": "60.2K",
			"link": "https://www.youtube.com/watch?v=VWzRVC3v20Y"
		},
		{
			"title": "EVERYTHING",
			"rank": "93",
			"lastWeekRank": "지난주 #89",
			"albumImg": "https://i.ytimg.com/vi/Aq_gsctWHtQ/mqdefault.jpg",
			"singer": "검정치마",
			"chartDuration": "17주",
			"views": "59.8K",
			"link": "https://www.youtube.com/watch?v=Aq_gsctWHtQ"
		},
		{
			"title": "Backlight (UTA from ONE PIECE FILM RED)",
			"rank": "94",
			"lastWeekRank": "지난주 #70",
			"albumImg": "https://i.ytimg.com/vi/gt-v_YCkaMY/mqdefault.jpg",
			"singer": "Ado",
			"chartDuration": "3주",
			"views": "59.8K",
			"link": "https://www.youtube.com/watch?v=gt-v_YCkaMY"
		},
		{
			"title": "Overdose",
			"rank": "95",
			"lastWeekRank": "지난주 #84",
			"albumImg": "https://i.ytimg.com/vi/H08YWE4CIFQ/mqdefault.jpg",
			"singer": "Natori",
			"chartDuration": "7주",
			"views": "57.8K",
			"link": "https://www.youtube.com/watch?v=H08YWE4CIFQ"
		},
		{
			"title": "에잇",
			"rank": "96",
			"lastWeekRank": "지난주 #77",
			"albumImg": "https://i.ytimg.com/vi/Cxzzg7L3Xgc/mqdefault.jpg",
			"singer": "아이유(IU)",
			"chartDuration": "12주",
			"views": "57.7K",
			"link": "https://www.youtube.com/watch?v=Cxzzg7L3Xgc"
		},
		{
			"title": "Hype Boy (Performance ver.2)",
			"rank": "97",
			"lastWeekRank": "지난주 #93",
			"albumImg": "https://i.ytimg.com/vi/S4UEJePR0UE/mqdefault.jpg",
			"singer": "NewJeans",
			"chartDuration": "6주",
			"views": "57.5K",
			"link": "https://www.youtube.com/watch?v=S4UEJePR0UE"
		},
		{
			"title": "New Genesis",
			"rank": "98",
			"lastWeekRank": "지난주 #76",
			"albumImg": "https://i.ytimg.com/vi/1FliVTcX8bQ/mqdefault.jpg",
			"singer": "Ado",
			"chartDuration": "4주",
			"views": "57.4K",
			"link": "https://www.youtube.com/watch?v=1FliVTcX8bQ"
		},
		{
			"title": "Cure For Me (Official Video)",
			"rank": "99",
			"lastWeekRank": "지난주 #100",
			"albumImg": "https://i.ytimg.com/vi/K17df81RL9Y/mqdefault.jpg",
			"singer": "AURORA",
			"chartDuration": "5주",
			"views": "57.1K",
			"link": "https://www.youtube.com/watch?v=K17df81RL9Y"
		},
		{
			"title": "Celebrate",
			"rank": "100",
			"lastWeekRank": "--",
			"albumImg": "https://i.ytimg.com/vi/4bRuhofxsQ4/mqdefault.jpg",
			"singer": "슈퍼주니어",
			"chartDuration": "1주",
			"views": "57K",
			"link": "https://www.youtube.com/watch?v=4bRuhofxsQ4"
		}
	]
}